[{"status": "etab", "organisme": "ADDECCA - DDEC22", "coordinates": [48.5212054, -2.7316188], "couleur": "lightred", "infos": "ADDECCA - DDEC22<br>2021-1-FR01-KA120-SCH-000042690<br>SAINT-BRIEUC(22000)<br/>7 rue Jules Verne"}, {"status": "etab", "organisme": "LPO la fontaine des eaux", "coordinates": [48.4636912, -2.0376081], "couleur": "lightred", "infos": "LPO la fontaine des eaux<br>2021-1-FR01-KA120-SCH-000045361<br>Dinan(22100)<br/>48 promenade fontaine des eaux"}, {"status": "etab", "organisme": "OGEC SAINT GABRIEL", "coordinates": [47.8601642, -4.215391], "couleur": "lightred", "infos": "OGEC SAINT GABRIEL<br>2021-1-FR01-KA120-SCH-000046359<br>PONT L ABBE(29120)<br/>23 rue Jean Lautredou"}, {"status": "etab", "organisme": "OGEC GROUPE SCOLAIRE SAINTE ANNE", "coordinates": [48.3966514, -4.4902268], "couleur": "lightred", "infos": "OGEC GROUPE SCOLAIRE SAINTE ANNE<br>2021-1-FR01-KA120-SCH-000045811<br>BREST(29200)<br/>20 RUE LAMOTTE PICQUET"}, {"status": "etab", "organisme": "LYCEE LES VERGERS", "coordinates": [48.5515082, -1.7568085], "couleur": "lightred", "infos": "LYCEE LES VERGERS<br>2021-1-FR01-KA120-SCH-000042158<br>DOL DE BRETAGNE(35120)<br/>4 RUE DES MURETS"}, {"status": "etab", "organisme": "college le chene vert", "coordinates": [47.8453149, -1.6876254], "couleur": "lightred", "infos": "college le chene vert<br>2021-1-FR01-KA120-SCH-000046338<br>BAIN DE BRETAGNE(35470)<br/>2 RUE DU CHENE VERT"}, {"status": "etab", "organisme": "GIP-FAR", "coordinates": [48.1106679, -1.6737728], "couleur": "lightred", "infos": "GIP-FAR<br>2021-1-FR01-KA120-SCH-000047425<br>Rennes(35706)<br/>6, rue Kl\u00e9ber"}, {"status": "etab", "organisme": "OGEC St Joseph", "coordinates": [47.7511256, -3.3919957], "couleur": "lightred", "infos": "OGEC St Joseph<br>2021-1-FR01-KA120-SCH-000042853<br>LORIENT(56100)<br/>42 RUE DE KERGUESTENEN"}, {"status": "etab", "organisme": "Lyc\u00e9e Marcelin Berthelot", "coordinates": [47.6621376, -2.4601643], "couleur": "lightred", "infos": "Lyc\u00e9e Marcelin Berthelot<br>2021-1-FR01-KA120-SCH-000043387<br>Questembert(56230)<br/>Avenue Roland Garros"}, {"status": "etab", "organisme": "LYCEE POLYVALENT BROCELIANDE", "coordinates": [47.942942, -2.1308856], "couleur": "lightred", "infos": "LYCEE POLYVALENT BROCELIANDE<br>2021-1-FR01-KA120-SCH-000043153<br>Guer(56380)<br/>Bellevue"}, {"status": "etab", "organisme": "Lyc\u00e9e Benjamin Franklin", "coordinates": [47.6714048, -2.9812875], "couleur": "lightred", "infos": "Lyc\u00e9e Benjamin Franklin<br>2021-1-FR01-KA120-SCH-000045913<br>Auray(56400)<br/>1 rue de la for\u00eat"}, {"status": "etab", "organisme": "OGEC St JEAN-BAPTISTE", "coordinates": [47.6306737, -2.8219243], "couleur": "lightred", "infos": "OGEC St JEAN-BAPTISTE<br>2021-1-FR01-KA120-SCH-000045771<br>ARRADON (56)(56610)<br/>18 rue Bouruet Aubertot"}, {"status": "etab", "organisme": "ECOLE PRIVEE SAINT LOUIS", "coordinates": [47.9345297, -2.4027673], "couleur": "lightred", "infos": "ECOLE PRIVEE SAINT LOUIS<br>2021-1-FR01-KA120-SCH-000043272<br>PLOERMEL(56800)<br/>RIOUST DES VILLES AUDRAINS"}, {"status": "etab", "organisme": "college le chene vert", "coordinates": [47.8453149, -1.6876254], "couleur": "lightred", "infos": "college le chene vert<br>2022-1-FR01-KA121-SCH-000052640<br>BAIN DE BRETAGNE(35470)<br/>2 RUE DU CHENE VERT"}, {"status": "etab", "organisme": "OGEC St Joseph", "coordinates": [47.7511256, -3.3919957], "couleur": "lightred", "infos": "OGEC St Joseph<br>2022-1-FR01-KA121-SCH-000052646<br>LORIENT(56100)<br/>42 RUE DE KERGUESTENEN"}, {"status": "etab", "organisme": "Conseil National de l'Enseignement Agricole Priv\u00e9 Bretagne", "coordinates": [47.6586772, -2.7599079], "couleur": "lightred", "infos": "Conseil National de l'Enseignement Agricole Priv\u00e9 Bretagne<br>2022-1-FR01-KA121-SCH-000052520<br>VANNES(56000)<br/>CAMPUS DU VINCIN - CAR GIRATOIRE DE L'UNIVERSITE"}, {"status": "etab", "organisme": "Lyc\u00e9e Amiral Ronarc'h", "coordinates": [48.3754197, -4.5823021], "couleur": "lightred", "infos": "Lyc\u00e9e Amiral Ronarc'h<br>2022-1-FR01-KA121-SCH-000052631<br>BREST(29280)<br/>3 rue Mozart"}, {"status": "etab", "organisme": "Lyc\u00e9e Benjamin Franklin", "coordinates": [47.6714048, -2.9812875], "couleur": "lightred", "infos": "Lyc\u00e9e Benjamin Franklin<br>2022-1-FR01-KA121-SCH-000057149<br>Auray(56400)<br/>1 rue de la for\u00eat"}, {"status": "etab", "organisme": "Lyc\u00e9e  g\u00e9n\u00e9ral technologique Jean Moulin", "coordinates": [48.1940326, -4.0889105], "couleur": "lightred", "infos": "Lyc\u00e9e  g\u00e9n\u00e9ral technologique Jean Moulin<br>2022-1-FR01-KA121-SCH-000061609<br>Chateaulin(29150)<br/>10 rue du Lyc\u00e9e"}, {"status": "etab", "organisme": "OGEC St JEAN-BAPTISTE", "coordinates": [47.6306737, -2.8219243], "couleur": "lightred", "infos": "OGEC St JEAN-BAPTISTE<br>2022-1-FR01-KA121-SCH-000061684<br>ARRADON(56610)<br/>18 rue Bouruet Aubertot"}, {"status": "etab", "organisme": "LYCEE POLYVALENT BROCELIANDE", "coordinates": [47.942942, -2.1308856], "couleur": "lightred", "infos": "LYCEE POLYVALENT BROCELIANDE<br>2022-1-FR01-KA121-SCH-000061828<br>Guer(56380)<br/>Bellevue"}, {"status": "etab", "organisme": "Lyc\u00e9e Saint Esprit", "coordinates": [48.5131565, -4.080054586885245], "couleur": "lightred", "infos": "Lyc\u00e9e Saint Esprit<br>2022-1-FR01-KA121-SCH-000062346<br>LANDIVISIAU(29400)<br/>3 rue Emile Souvestre"}, {"status": "etab", "organisme": "D\u00e9partement d'Ille-et-Vilaine", "coordinates": [48.1267495, -1.6940874811968918], "couleur": "lightred", "infos": "D\u00e9partement d'Ille-et-Vilaine<br>2022-1-FR01-KA121-SCH-000062624<br>RENNES(35000)<br/>1 Avenue de la pr\u00e9fecture"}, {"status": "etab", "organisme": "OGEC SAINT GABRIEL", "coordinates": [47.8601642, -4.215391], "couleur": "lightred", "infos": "OGEC SAINT GABRIEL<br>2022-1-FR01-KA121-SCH-000062907<br>PONT L ABBE(29120)<br/>23 rue Jean Lautredou"}, {"status": "etab", "organisme": "LPO la fontaine des eaux", "coordinates": [48.4636912, -2.0376081], "couleur": "lightred", "infos": "LPO la fontaine des eaux<br>2022-1-FR01-KA121-SCH-000063528<br>Dinan(22100)<br/>48 promenade fontaine des eaux"}, {"status": "etab", "organisme": "OGEC SAINTE THERESE LES BUISSONNET", "coordinates": [47.991426, -4.0900368], "couleur": "lightred", "infos": "OGEC SAINTE THERESE LES BUISSONNET<br>2022-1-FR01-KA121-SCH-000063924<br>Quimper(29000)<br/>75, avenue de Kergoat Al Lez"}, {"status": "etab", "organisme": "ECOLE PRIVEE SAINT LOUIS", "coordinates": [47.9345297, -2.4027673], "couleur": "lightred", "infos": "ECOLE PRIVEE SAINT LOUIS<br>2022-1-FR01-KA121-SCH-000063977<br>PLOERMEL(56800)<br/>RIOUST DES VILLES AUDRAINS"}, {"status": "etab", "organisme": "Direction Dioc\u00e9saine de l'Enseignement Catholique du Morbihan", "coordinates": [47.62798, -2.8229152], "couleur": "lightred", "infos": "Direction Dioc\u00e9saine de l'Enseignement Catholique du Morbihan<br>2022-1-FR01-KA121-SCH-000064393<br>ARRADON(56610)<br/>Le Vincin - 3 all\u00e9e des Foug\u00e8res"}, {"status": "etab", "organisme": "ADDECCA - DDEC22", "coordinates": [48.5212054, -2.7316188], "couleur": "lightred", "infos": "ADDECCA - DDEC22<br>2022-1-FR01-KA121-SCH-000064696<br>SAINT-BRIEUC(22000)<br/>7 rue Jules Verne"}, {"status": "etab", "organisme": "OGEC GROUPE SCOLAIRE SAINTE ANNE", "coordinates": [48.3966514, -4.4902268], "couleur": "lightred", "infos": "OGEC GROUPE SCOLAIRE SAINTE ANNE<br>2022-1-FR01-KA121-SCH-000065188<br>BREST(29200)<br/>20 RUE LAMOTTE PICQUET"}, {"status": "etab", "organisme": "Association Dioc\u00e9saine De l'Enseignement Catholique Finist\u00e8re", "coordinates": [47.9999054, -4.0962937], "couleur": "lightred", "infos": "Association Dioc\u00e9saine De l'Enseignement Catholique Finist\u00e8re<br>2022-1-FR01-KA121-SCH-000065170<br>QUIMPER(29000)<br/>2 rue C\u00e9sar Franck"}, {"status": "etab", "organisme": "GROUPE SCOLAIRE D'ENSEIGNEMENT AGRICOLE PRIVE ANTOINE DE SAINT-EXUPERY", "coordinates": [48.1317237, -1.7060519], "couleur": "lightred", "infos": "GROUPE SCOLAIRE D'ENSEIGNEMENT AGRICOLE PRIVE ANTOINE DE SAINT-EXUPERY<br>2022-1-FR01-KA121-SCH-000068037<br>RENNES(35043)<br/>Rue Fernand Robert"}, {"status": "etab", "organisme": "GIP-FAR", "coordinates": [48.1106679, -1.6737728], "couleur": "lightred", "infos": "GIP-FAR<br>2022-1-FR01-KA121-SCH-000068506<br>Rennes(35706)<br/>6, rue Kl\u00e9ber"}, {"status": "etab", "organisme": "Lyc\u00e9e Marcelin Berthelot", "coordinates": [47.6621376, -2.4601643], "couleur": "lightred", "infos": "Lyc\u00e9e Marcelin Berthelot<br>2022-1-FR01-KA121-SCH-000068297<br>Questembert(56230)<br/>Avenue Roland Garros"}, {"status": "etab", "organisme": "LYCEE LES VERGERS", "coordinates": [48.5515082, -1.7568085], "couleur": "lightred", "infos": "LYCEE LES VERGERS<br>2022-1-FR01-KA121-SCH-000068532<br>DOL DE BRETAGNE(35120)<br/>4 RUE DES MURETS"}, {"status": "etab", "organisme": "COLLEGE GWER HALOU", "coordinates": [48.406432, -3.430008], "couleur": "lightred", "infos": "COLLEGE GWER HALOU<br>2022-1-FR01-KA122-SCH-000075181<br>CALLAC(22160)<br/>16 RUE ANATOLE LE BRAZ"}, {"status": "etab", "organisme": "OGEC NOTRE DAME DES VICTOIRES", "coordinates": [48.5127551, -4.0699356], "couleur": "lightred", "infos": "OGEC NOTRE DAME DES VICTOIRES<br>2022-1-FR01-KA122-SCH-000076988<br>LANDIVISIAU(29400)<br/>23 rue du G\u00e9n\u00e9ral Mangin"}, {"status": "etab", "organisme": "Association Direction Dioc\u00e9saine de l Enseignement Catholique d Ille et Vilaine", "coordinates": [48.1134164, -1.6985292], "couleur": "lightred", "infos": "Association Direction Dioc\u00e9saine de l Enseignement Catholique d Ille et Vilaine<br>2022-1-FR01-KA122-SCH-000078012<br>Rennes(35043)<br/>45 rue de Brest"}, {"status": "etab", "organisme": "OGEC Ecole Priv\u00e9e La Chapelle-Janson", "coordinates": [48.34859185, -1.102699586527912], "couleur": "lightred", "infos": "OGEC Ecole Priv\u00e9e La Chapelle-Janson<br>2022-1-FR01-KA122-SCH-000078115<br>La Chapelle-Janson(35133)<br/>16, rue du bas bourg"}, {"status": "etab", "organisme": "Association Gestion Enseignement Catholique Jean-Baptiste LE TAILLANDIER", "coordinates": [48.3567714, -1.2043652], "couleur": "lightred", "infos": "Association Gestion Enseignement Catholique Jean-Baptiste LE TAILLANDIER<br>2022-1-FR01-KA122-SCH-000074221<br>FOUGERES(35300)<br/>9 bis rue Eug\u00e8ne Pacory"}, {"status": "etab", "organisme": "SAINT FRANCOIS XAVIER", "coordinates": [47.6542673, -2.7601146], "couleur": "lightred", "infos": "SAINT FRANCOIS XAVIER<br>2022-1-FR01-KA122-SCH-000078954<br>VANNES(56000)<br/>3 RUE THIERS"}, {"status": "etab", "organisme": "LA MAILLETTE NOTRE DAME DU PLASKER", "coordinates": [47.8896564, -2.835546], "couleur": "lightred", "infos": "LA MAILLETTE NOTRE DAME DU PLASKER<br>2022-1-FR01-KA122-SCH-000078575<br>LOCMINE(56500)<br/>8 rue Jean-Marie de Lamennais"}]